Metadata-Version: 1.2
Name: FragPELE
Version: 2.1.1
Summary: FragPELE, a new tool for in silico hit-to-lead drug design, capable of growing a frag_pelement into a core while exploring the protein-ligand conformational space
Home-page: https://github.com/carlesperez94/frag_pele/
Author: Carles Perez Lopez, Daniel Soler Viladrich
Author-email: daniel.soler@nostrumbiodiscovery.com, carlesperez94@gmail.com
License: UNKNOWN
Project-URL: Documentation, https://carlesperez94.github.io/frag_pele/
Project-URL: Source, https://carlesperez94.github.io/frag_pele/
Project-URL: Tracker, https://github.com/carlesperez94/frag_pele/issues
Platform: UNKNOWN
Classifier: Programming Language :: Python :: 3
Classifier: Programming Language :: Python :: 2.7
Classifier: License :: OSI Approved :: MIT License
Classifier: Operating System :: POSIX :: Linux
Classifier: Intended Audience :: Science/Research
